<?xml version="1.0" encoding="utf-8"?>

<document xmlns:xtf="http://cdlib.org/xtf">
    <title>Orange and Blue: Colors That Don't Work Together</title>
    <creator>Jeffy Color Wheel</creator>
    <subject>Fribble Color Wheel Smarmy</subject>
    <type>text</type>
    <identifier xtf:store="false">http://ark.cdlib.org/ark:/13030/7z35ss92</identifier>
    <relation>http://www.orangecrush.com/</relation>
    <rights xtf:index="no">Public</rights>
    <foo>bar</foo>
    <family xtf:meta="yes" xtf:store="no">O'Connell family</family>
</document>