<?xml version="1.0" encoding="UTF-8"?>
<transTable>
    <trans>
        <from>Add</from>
        <to>Hinzufügen</to>
    </trans>
    <trans>
        <from>Advanced</from>
        <to>Erweiterte Suche</to>
    </trans>
    <trans>
        <from>author</from>
        <to>autor</to>
    </trans>
    <trans>
        <from>Author</from>
        <to>Autor</to>
    </trans>
    <trans>
        <from>Bookbag</from>
        <to>Zwischenablage</to>
    </trans>
    <trans>
        <from>Browse</from>
        <to>Browsen</to>
    </trans>
    <trans>
        <from>Browse by</from>
        <to>Browsen:</to>
    </trans>
    <trans>
        <from>Choose Language</from>
        <to>Wählen Sie eine Sprache</to>
    </trans>
    <trans>
        <from>Citation</from>
        <to>Zitat</to>
    </trans>
    <trans>
        <from>Clear</from>
        <to>Reset</to>
    </trans>
    <trans>
        <from>Clear Hits</from>
        <to>Reset</to>
    </trans>
    <trans>
        <from>Collapse All</from>
        <to>Zusammenbruch Alle</to>
    </trans>
    <trans>
        <from>Comments? Questions?</from>
        <to>Kommentare? Fragen?</to>
    </trans>
    <trans>
        <from>Date</from>
        <to>Erscheinungsjahr</to>
    </trans>
    <trans>
        <from>Did you mean to search for</from>
        <to>Meinten Sie</to>
    </trans>
    <trans>
        <from>Expand All</from>
        <to>Erweitern Alle</to>
    </trans>
    <trans>
        <from>Facet</from>
        <to>Suche verfeinern</to>
    </trans>
    <trans>
        <from>Freeform</from>
        <to>Freiform</to>
    </trans>
    <trans>
        <from>Go!</from>
        <to>Los!</to>
    </trans>
    <trans>
        <from>Home</from>
        <to>Startseite</to>
    </trans>
    <trans>
        <from>Keyword</from>
        <to>Stichwort</to>
    </trans>
    <trans>
        <from>Matches</from>
        <to>Suchergebnisse</to>
    </trans>
    <trans>
        <from>Modify Search</from>
        <to>Suche Ändern</to>
    </trans>
    <trans>
        <from>New Search</from>
        <to>Neue Suche</to>
    </trans>
    <trans>
        <from>occurrences of</from>
        <to>vorkommen von</to>
    </trans>
    <trans>
        <from>Page</from>
        <to>Seite</to>
    </trans>
    <trans>
        <from>Print View</from>
        <to>Druckansicht</to>
    </trans>
    <trans>
        <from>publication date</from>
        <to>Erscheinungsdatum</to>
    </trans>
    <trans>
        <from>Published</from>
        <to>Erscheint</to>
    </trans>
    <trans>
        <from>relevance</from>
        <to>relevanz</to>
    </trans>
    <trans>
        <from>Results</from>
        <to>Ergebnisliste</to>
    </trans>
    <trans>
        <from>Return to Search Results</from>
        <to>Züruck zur Ergebnisliste</to>
    </trans>
    <trans>
        <from>reverse date</from>
        <to>reverse datum</to>
    </trans>
    <trans>
        <from>Search</from>
        <to>Suche</to>
    </trans>
    <trans>
        <from>Search this Item</from>
        <to>Suchen Sie diesen Artikel</to>
    </trans>
    <trans>
        <from>Similar&#160;Items</from>
        <to>Ähnliche:</to>
    </trans>
    <trans>
        <from>Sorted by</from>
        <to>Sortiert nach</to>
    </trans>
    <trans>
        <from>Subject</from>
        <to>Thema</to>
    </trans>
    <trans>
        <from>Subjects</from>
        <to>Themen</to>
    </trans>
    <trans>
        <from>title</from>
        <to>titel</to>
    </trans>
    <trans>
        <from>Title</from>
        <to>Titel</to>
    </trans>
</transTable>